{"نیکو": {"خوراک کباب کوبیده": "۸۰,۰۰۰ تومان", "چلو کباب کوبیده": "۲۱۵,۰۰۰ تومان", "چلو جوجه کباب زعفرانی": "۱۶۰,۰۰۰ تومان", "خوراک جوجه کباب زعفرانی": "۱۰۵,۰۰۰ تومان", "چلو مرغ سس پز": "۱۵۵,۰۰۰ تومان", "خورشت ماست": "۸۳,۰۰۰ تومان", "خوراک جوجه چینی با سس تارتار": "۱۳۰,۰۰۰ تومان", "خوراک مرغ ربی": "۱۰۰,۰۰۰ تومان", "False": "False", "چلو کباب میکس": "۲۷۵,۰۰۰ تومان", "چلو جوجه کباب لاری": "۲۰۵,۰۰۰ تومان", "چلو جوجه کباب ترش": "۲۰۵,۰۰۰ تومان", "چلو کباب کوبیده مرغ": "۱۵۵,۰۰۰ تومان", "چلو ساده": "۵۵,۰۰۰ تومان", "خوراک جوجه کباب لاری": "۱۵۰,۰۰۰ تومان", "خوراک جوجه کباب ترش": "۱۵۰,۰۰۰ تومان", "خوراک کباب کوبیده مرغ": "۵۰,۰۰۰ تومان", "چلو جوجه چینی با سس تارتار": "۱۸۵,۰۰۰ تومان", "چلو خورشت قیمه سیب زمینی": "۱۰۵,۰۰۰ تومان", "خورشت قیمه سیب زمینی": "۵۰,۰۰۰ تومان", "چلو خورشت قورمه سبزی": "۱۰۵,۰۰۰ تومان", "خورشت قورمه سبزی": "۵۰,۰۰۰ تومان", "چلو خورشت بادمجان": "۱۰۰,۰۰۰ تومان", "خورشت بادمجان": "۴۵,۰۰۰ تومان", "چلو خورشت فسنجان ملس": "۱۷۵,۰۰۰ تومان", "خورشت فسنجان ملس": "۱۲۰,۰۰۰ تومان", "عدس پلو با گوشت": "۵۵,۰۰۰ تومان", "سالاد فصل": "۲۰,۰۰۰ تومان", "سالاد شیرازی": "۲۰,۰۰۰ تومان", "سوپ جو": "۶۰,۰۰۰ تومان", "کوکو قندی": "۶۰,۰۰۰ تومان", "نوشابه بطری": "۱۴,۰۰۰ تومان", "نوشابه قوطی": "۲۲,۰۰۰ تومان", "نوشابه خانواده": "۳۶,۳۰۰ تومان", "ماءالشعیر شیشه ای هی دی": "۲۲,۰۰۰ تومان", "ماءالشعیر خانواده هی دی": "۳۷,۰۰۰ تومان", "دوغ بطری سنتی": "۱۲,۰۰۰ تومان", "دوغ خانواده سنتی": "۴۰,۰۰۰ تومان"}}